README
_imaging.c
setup.cfg
setup.py
Omelette.egg-info/PKG-INFO
Omelette.egg-info/SOURCES.txt
Omelette.egg-info/dependency_links.txt
Omelette.egg-info/top_level.txt
PIL/ArgImagePlugin.py
PIL/BdfFontFile.py
PIL/BmpImagePlugin.py
PIL/BufrStubImagePlugin.py
PIL/ContainerIO.py
PIL/CurImagePlugin.py
PIL/DcxImagePlugin.py
PIL/EpsImagePlugin.py
PIL/ExifTags.py
PIL/FitsStubImagePlugin.py
PIL/FliImagePlugin.py
PIL/FontFile.py
PIL/FpxImagePlugin.py
PIL/GbrImagePlugin.py
PIL/GdImageFile.py
PIL/GifImagePlugin.py
PIL/GimpGradientFile.py
PIL/GimpPaletteFile.py
PIL/GribStubImagePlugin.py
PIL/Hdf5StubImagePlugin.py
PIL/IcnsImagePlugin.py
PIL/IcoImagePlugin.py
PIL/ImImagePlugin.py
PIL/Image.py
PIL/ImageChops.py
PIL/ImageColor.py
PIL/ImageDraw.py
PIL/ImageDraw2.py
PIL/ImageEnhance.py
PIL/ImageFile.py
PIL/ImageFileIO.py
PIL/ImageFilter.py
PIL/ImageFont.py
PIL/ImageGL.py
PIL/ImageGrab.py
PIL/ImageMath.py
PIL/ImageMode.py
PIL/ImageOps.py
PIL/ImagePalette.py
PIL/ImagePath.py
PIL/ImageQt.py
PIL/ImageSequence.py
PIL/ImageStat.py
PIL/ImageTk.py
PIL/ImageTransform.py
PIL/ImageWin.py
PIL/ImtImagePlugin.py
PIL/IptcImagePlugin.py
PIL/JpegImagePlugin.py
PIL/McIdasImagePlugin.py
PIL/MicImagePlugin.py
PIL/MpegImagePlugin.py
PIL/MspImagePlugin.py
PIL/OleFileIO.py
PIL/PSDraw.py
PIL/PaletteFile.py
PIL/PalmImagePlugin.py
PIL/PcdImagePlugin.py
PIL/PcfFontFile.py
PIL/PcxImagePlugin.py
PIL/PdfImagePlugin.py
PIL/PixarImagePlugin.py
PIL/PngImagePlugin.py
PIL/PpmImagePlugin.py
PIL/PsdImagePlugin.py
PIL/SgiImagePlugin.py
PIL/SpiderImagePlugin.py
PIL/SunImagePlugin.py
PIL/TarIO.py
PIL/TgaImagePlugin.py
PIL/TiffImagePlugin.py
PIL/TiffTags.py
PIL/WalImageFile.py
PIL/WmfImagePlugin.py
PIL/XVThumbImagePlugin.py
PIL/XbmImagePlugin.py
PIL/XpmImagePlugin.py
PIL/__init__.py
Scripts/pilconvert.py
Scripts/pildriver.py
Scripts/pilfile.py
Scripts/pilfont.py
Scripts/pilprint.py