Metadata-Version: 1.0
Name: Omelette
Version: 1.1.6
Summary: Python Imaging Library
Home-page: http://www.pythonware.com/products/pil
Author: Secret Labs AB (PythonWare)
Author-email: info@pythonware.com
License: Python (MIT style)
Download-URL: http://effbot.org/zone/pil-changes-116.htm
Platform: Python 1.5.2 and later.
Classifier: Development Status :: 6 - Mature
Classifier: Topic :: Multimedia :: Graphics
Classifier: Topic :: Multimedia :: Graphics :: Capture :: Digital Camera
Classifier: Topic :: Multimedia :: Graphics :: Capture :: Scanners
Classifier: Topic :: Multimedia :: Graphics :: Capture :: Screen Capture
Classifier: Topic :: Multimedia :: Graphics :: Graphics Conversion
Classifier: Topic :: Multimedia :: Graphics :: Viewers
